pyepidemics/__init__.py
pyepidemics/curve_fitting.py
pyepidemics/utils.py
pyepidemics/dataset/__init__.py
pyepidemics/dataset/_base.py
pyepidemics/dataset/_build.py
pyepidemics/dataset/_fetch.py
pyepidemics/dataset/_fetch_bed.py
pyepidemics/dataset/_fetch_geojson.py
pyepidemics/models/__init__.py
pyepidemics/models/model.py
pyepidemics/models/network.py
pyepidemics/models/params.py
pyepidemics/models/state.py
pyepidemics/models/states.py
pyepidemics/models/examples/__init__.py
pyepidemics/models/examples/covid.py
pyepidemics/models/examples/covid_category.py
pyepidemics/models/examples/covid_prodromal.py
pyepidemics/models/examples/granular_sir.py
pyepidemics/models/examples/seidr.py
pyepidemics/models/examples/seihdr.py
pyepidemics/models/examples/seir.py
pyepidemics/models/examples/sir.py
pyepidemics/params/__init__.py
pyepidemics/params/bayesian_optimizer.py
pyepidemics/params/hyperopt_optimizer.py
pyepidemics/params/metrics.py
pyepidemics/params/neptune.py
pyepidemics/params/optimizer.py
pyepidemics/params/utils.py
pyepidemics/policies/__init__.py
pyepidemics/policies/contact.py
pyepidemics/policies/utils.py
pyepidemics/visualization/__init__.py
pyepidemics/visualization/map.py
pyepidemics-0.0.9.dist-info/LICENSE
pyepidemics-0.0.9.dist-info/METADATA
pyepidemics-0.0.9.dist-info/WHEEL
pyepidemics-0.0.9.dist-info/top_level.txt
pyepidemics-0.0.9.dist-info/RECORD
