Metadata-Version: 2.1
Name: pyepidemics
Version: 0.0.9
Summary: Open source epidemiological modeling in Python
Home-page: https://github.com/collectif-codata/pyepidemics
Author: Theo Alves Da Costa
Author-email: theo.alvesdacosta@ekimetrics.com
License: UNKNOWN
Project-URL: Documentation, https://collectif-codata.github.io/pyepidemics/
Platform: UNKNOWN
Classifier: Development Status :: 3 - Alpha
Classifier: Programming Language :: Python :: 3
Classifier: License :: OSI Approved :: MIT License
Classifier: Operating System :: OS Independent
Requires-Python: >=3.6
Requires-Dist: scipy (==1.4.1)
Requires-Dist: numpy (==1.18.4)
Requires-Dist: pandas (>=1.0.0)
Requires-Dist: scikit-learn (==0.23.1)
Requires-Dist: matplotlib (==3.1.3)
Requires-Dist: optuna (==1.3.0)
Requires-Dist: pydeck (==0.3.0b2)
Requires-Dist: requests (==2.22.0)
Requires-Dist: plotly (==4.6.0)
Requires-Dist: tqdm (==4.46.0)
Requires-Dist: statsmodels (==0.10.1)
Requires-Dist: networkx (==2.3)
Requires-Dist: PyYAML (==5.3.1)
Requires-Dist: xlrd (>=1.0.0)
